plugins/starzai_memu/__init__.py
plugins/starzai_memu/config.py
StarZai_Memu-0.1.0.dist-info/METADATA
StarZai_Memu-0.1.0.dist-info/WHEEL
StarZai_Memu-0.1.0.dist-info/top_level.txt
StarZai_Memu-0.1.0.dist-info/RECORD
