Metadata-Version: 2.1
Name: StarZai-Memu
Version: 0.1.0
Summary: StarZai-Memu
Requires-Python: <4.0,>=3.8
